face_search/__init__.py
face_search/cache.py
face_search/cli.py
face_search/cooccurrence.py
face_search/core.py
face_search/detectors.py
face_search/embedders.py
face_search/gui.py
face_search/index.py
face_search/interfaces.py
face_search/loaders.py
face_search/models.py
face_search-0.2.1.dist-info/licenses/LICENSE
face_search-0.2.1.dist-info/METADATA
face_search-0.2.1.dist-info/WHEEL
face_search-0.2.1.dist-info/entry_points.txt
face_search-0.2.1.dist-info/top_level.txt
face_search-0.2.1.dist-info/RECORD
