Metadata-Version: 2.4
Name: face-search
Version: 0.2.1
Summary: AI-powered face search for photo libraries
Author: Emin Genç
License: AGPL-3.0
Project-URL: Homepage, https://github.com/emingenc/face-search
Project-URL: Repository, https://github.com/emingenc/face-search
Project-URL: Documentation, https://github.com/emingenc/face-search#readme
Project-URL: Bug Tracker, https://github.com/emingenc/face-search/issues
Keywords: face-recognition,face-search,photo-management,ai,computer-vision
Classifier: Development Status :: 4 - Beta
Classifier: Intended Audience :: Developers
Classifier: Intended Audience :: End Users/Desktop
Classifier: License :: OSI Approved :: GNU Affero General Public License v3
Classifier: Programming Language :: Python :: 3
Classifier: Programming Language :: Python :: 3.8
Classifier: Programming Language :: Python :: 3.9
Classifier: Programming Language :: Python :: 3.10
Classifier: Programming Language :: Python :: 3.11
Classifier: Topic :: Multimedia :: Graphics
Classifier: Topic :: Scientific/Engineering :: Artificial Intelligence
Requires-Python: >=3.8
License-File: LICENSE
Requires-Dist: deepface>=0.0.79
Requires-Dist: faiss-cpu>=1.7.4
Requires-Dist: opencv-python-headless>=4.8.0
Requires-Dist: numpy>=1.21.0
Requires-Dist: tqdm>=4.65.0
Requires-Dist: click>=8.0.0
Requires-Dist: tf-keras==2.20.1
Provides-Extra: dev
Requires-Dist: pytest>=7.0.0; extra == "dev"
Requires-Dist: pytest-cov>=4.0.0; extra == "dev"
Requires-Dist: black>=23.0.0; extra == "dev"
Requires-Dist: flake8>=6.0.0; extra == "dev"
Provides-Extra: gui
Requires-Dist: gradio>=3.50.0; extra == "gui"
Dynamic: license-file
